instana_client/__init__.py
instana_client/api_client.py
instana_client/api_response.py
instana_client/configuration.py
instana_client/exceptions.py
instana_client/py.typed
instana_client/rest.py
instana_client/api/__init__.py
instana_client/api/action_catalog_api.py
instana_client/api/action_history_api.py
instana_client/api/ai_management_api.py
instana_client/api/apdex_report_api.py
instana_client/api/apdex_settings_api.py
instana_client/api/api_token_api.py
instana_client/api/application_alert_configuration_api.py
instana_client/api/application_analyze_api.py
instana_client/api/application_catalog_api.py
instana_client/api/application_metrics_api.py
instana_client/api/application_resources_api.py
instana_client/api/application_settings_api.py
instana_client/api/application_topology_api.py
instana_client/api/audit_log_api.py
instana_client/api/authentication_api.py
instana_client/api/business_monitoring_api.py
instana_client/api/custom_dashboards_api.py
instana_client/api/custom_entities_api.py
instana_client/api/end_user_monitoring_api.py
instana_client/api/event_settings_api.py
instana_client/api/events_api.py
instana_client/api/global_application_alert_configuration_api.py
instana_client/api/groups_api.py
instana_client/api/health_api.py
instana_client/api/host_agent_api.py
instana_client/api/infrastructure_alert_configuration_api.py
instana_client/api/infrastructure_analyze_api.py
instana_client/api/infrastructure_catalog_api.py
instana_client/api/infrastructure_metrics_api.py
instana_client/api/infrastructure_resources_api.py
instana_client/api/infrastructure_topology_api.py
instana_client/api/log_alert_configuration_api.py
instana_client/api/logging_analyze_api.py
instana_client/api/maintenance_configuration_api.py
instana_client/api/mobile_app_analyze_api.py
instana_client/api/mobile_app_catalog_api.py
instana_client/api/mobile_app_configuration_api.py
instana_client/api/mobile_app_metrics_api.py
instana_client/api/policies_api.py
instana_client-1.0.2.dist-info/licenses/LICENSE
instana_client-1.0.2.dist-info/METADATA
instana_client-1.0.2.dist-info/WHEEL
instana_client-1.0.2.dist-info/top_level.txt
instana_client-1.0.2.dist-info/RECORD
