Metadata-Version: 2.4
Name: instana_client
Version: 1.0.2
Summary: Instana REST API documentation
Home-page: https://github.com/instana/client-python
Author: © Instana
Author-email: © Instana <support@instana.com>
Project-URL: Repository, https://github.com/instana/client-python
Keywords: OpenAPI,OpenAPI-Generator,Instana REST API documentation
Requires-Python: >=3.9
License-File: LICENSE
Requires-Dist: urllib3<3.0.0,>=2.1.0
Requires-Dist: python-dateutil>=2.8.2
Requires-Dist: pydantic>=2
Requires-Dist: typing-extensions>=4.7.1
Provides-Extra: dev
Requires-Dist: pytest>=7.2.1; extra == "dev"
Requires-Dist: pytest-cov>=2.8.1; extra == "dev"
Requires-Dist: tox>=3.9.0; extra == "dev"
Requires-Dist: flake8>=4.0.0; extra == "dev"
Requires-Dist: types-python-dateutil>=2.8.19.14; extra == "dev"
Requires-Dist: mypy>=1.5; extra == "dev"
Dynamic: author
Dynamic: home-page
Dynamic: license-file
